trashpanda.py
trashpanda-1.2.0.dist-info/LICENSE.md
trashpanda-1.2.0.dist-info/METADATA
trashpanda-1.2.0.dist-info/WHEEL
trashpanda-1.2.0.dist-info/top_level.txt
trashpanda-1.2.0.dist-info/RECORD
