Metadata-Version: 2.1
Name: trashpanda
Version: 1.2.0
Summary: Helper methods compounding tasks, which are not directly covered in pandas. (Or I didn't found them.)
Home-page: https://gitlab.com/david.scheliga/trashpanda
Author: David Scheliga
License: GNU General Public License V3 (GPLv3)
Project-URL: Documentation, https://trashpanda.readthedocs.io/en/latest/
Project-URL: Source Code Repository, https://gitlab.com/david.scheliga/trashpanda
Keywords: pandas,helper
Platform: UNKNOWN
Classifier: Development Status :: 5 - Production/Stable
Classifier: License :: OSI Approved :: GNU General Public License v3 (GPLv3)
Classifier: Operating System :: OS Independent
Classifier: Programming Language :: Python :: 3
Classifier: Programming Language :: Python :: 3.6
Classifier: Programming Language :: Python :: 3.7
Classifier: Programming Language :: Python :: 3.8
Classifier: Programming Language :: Python :: 3.9
License-File: LICENSE.md
Requires-Dist: pandas (>=1.0.0)
Requires-Dist: numpy (>=1.16.0)
